[
 {
  "allow_consecutive_login_attempts": 0,
  "allow_error_traceback": 0,
  "allow_guests_to_upload_files": 0,
  "allow_login_after_fail": 60,
  "allow_login_using_mobile_number": 0,
  "allow_login_using_user_name": 0,
  "app_name": "Frappe",
  "apply_strict_user_permissions": 0,
  "attach_view_link": 1,
  "backup_limit": 3,
  "bypass_2fa_for_retricted_ip_users": 0,
  "bypass_restrict_ip_check_if_2fa_enabled": 0,
  "country": "Germany",
  "currency_precision": "",
  "date_format": "dd.mm.yyyy",
  "deny_multiple_sessions": 0,
  "disable_standard_email_footer": 0,
  "docstatus": 0,
  "doctype": "System Settings",
  "dormant_days": 4,
  "email_footer_address": null,
  "enable_chat": 0,
  "enable_onboarding": 1,
  "enable_password_policy": 1,
  "enable_prepared_report_auto_deletion": 1,
  "enable_scheduler": 1,
  "enable_two_factor_auth": 0,
  "float_precision": "3",
  "force_user_to_reset_password": 0,
  "hide_footer_in_auto_email_reports": 0,
  "is_first_startup": 1,
  "language": "en",
  "lifespan_qrcode_image": 0,
  "logout_on_password_reset": 1,
  "minimum_password_score": "2",
  "modified": "2021-06-02 15:29:38.525994",
  "name": "System Settings",
  "number_format": "#.###,##",
  "otp_issuer_name": "Frappe Framework",
  "parent": null,
  "parentfield": null,
  "parenttype": null,
  "password_reset_limit": 3,
  "prepared_report_expiry_period": 30,
  "session_expiry": "06:00",
  "session_expiry_mobile": "720:00",
  "setup_complete": 1,
  "strip_exif_metadata_from_uploaded_images": 1,
  "time_format": "HH:mm",
  "time_zone": "Europe/Berlin",
  "two_factor_method": "OTP App"
 }
]